setup.py
commonutil_fileio_persistentqueue/__init__.py
commonutil_fileio_persistentqueue/textfolder.py
commonutil_fileio_persistentqueue.egg-info/PKG-INFO
commonutil_fileio_persistentqueue.egg-info/SOURCES.txt
commonutil_fileio_persistentqueue.egg-info/dependency_links.txt
commonutil_fileio_persistentqueue.egg-info/top_level.txt