Metadata-Version: 1.1
Name: commonutil-fileio-persistentqueue
Version: 3.0.2
Summary: Persistent queue on file system
Home-page: UNKNOWN
Author: UNKNOWN
Author-email: UNKNOWN
License: MIT License
Platform: UNKNOWN
Classifier: Development Status :: 5 - Production/Stable
Classifier: Intended Audience :: Developers
Classifier: License :: OSI Approved :: MIT License
Classifier: Operating System :: POSIX
Classifier: Programming Language :: Python :: 3.6
Classifier: Programming Language :: Python :: 3.7
